caer/README.md
caer/__init__.py
caer/_base.py
caer/_internal.py
caer/_meta.py
caer/core.py
caer/globals.py
caer/preprocess.py
caer/annotations/__init__.py
caer/color/__init__.py
caer/color/_bgr.py
caer/color/_constants.py
caer/color/_gray.py
caer/color/_hls.py
caer/color/_hsv.py
caer/color/_lab.py
caer/color/_luv.py
caer/color/_rgb.py
caer/color/_yuv.py
caer/color/core.py
caer/coreten/__init__.py
caer/coreten/_internal.py
caer/coreten/_tensor_base.py
caer/coreten/_tensor_str.py
caer/coreten/tensor.py
caer/data/__init__.py
caer/data/black_cat.jpg
caer/data/camera.jpg
caer/data/fighter_fish.jpg
caer/data/gold_fish.jpg
caer/data/guitar.jpg
caer/data/puppy.jpg
caer/data/snow.jpg
caer/data/sunrise.jpg
caer/data/tent.jpg
caer/io/__init__.py
caer/io/io.py
caer/io/resize.py
caer/path/__init__.py
caer/path/paths.py
caer/preprocessing/__init__.py
caer/preprocessing/mean_subtraction.py
caer/transforms/__init__.py
caer/transforms/blur.py
caer/transforms/color.py
caer/transforms/functional.py
caer/transforms/position.py
caer/transforms/simulate.py
caer/video/__init__.py
caer/video/constants.py
caer/video/extract_frames.py
caer/video/frames_and_fps.py
caer/video/gpufilestream.py
caer/video/livestream.py
caer/video/stream.py
caer-2.1.1.dist-info/LICENSE
caer-2.1.1.dist-info/METADATA
caer-2.1.1.dist-info/WHEEL
caer-2.1.1.dist-info/top_level.txt
caer-2.1.1.dist-info/RECORD
